fluffysnips/__init__.py
fluffysnips/mvscreenshot.py
fluffysnips/tablefix.py
fluffysnips-0.0.3.dist-info/METADATA
fluffysnips-0.0.3.dist-info/WHEEL
fluffysnips-0.0.3.dist-info/entry_points.txt
fluffysnips-0.0.3.dist-info/top_level.txt
fluffysnips-0.0.3.dist-info/RECORD
