Metadata-Version: 2.1
Name: fluffysnips
Version: 0.0.3
Summary: Various useful CLI tools
Home-page: https://github.com/jackadamson/fluffysnips
Author: Jack Adamson
Author-email: jack@mrfluffybunny.com
License: MIT
Platform: UNKNOWN
Classifier: Programming Language :: Python :: 3
Classifier: Operating System :: OS Independent
Requires-Python: >=3.7
Requires-Dist: typer
